实验3(SHA2)/sha_engine.v
module sha_engine(word,clk,index,rst,output_valid,hash_data,last_word,last_next);

input [31:0]word;
input clk,rst,last_word;
input [1:0]last_next;

reg [31:0]W[63:0];
output reg [6:0] index;
output [255:0]hash_data;
output reg output_valid;
reg [31:0]p,q,r,x,a,b,c,d,e,f,g,h,sum0,Ch,sum1,Maj,T1,T2;
reg [31:0]H[7:0];
reg [31:0]K[63:0];
reg D;

always @(negedge rst)
begin 
D = 1'b0;
index = 7'd126;
output_valid = 1'b0;
H[0] = 32'h6a09e667;
H[1] = 32'hbb67ae85;
H[2] = 32'h3c6ef372;
H[3] = 32'ha54ff53a;
H[4] = 32'h510e527f;
H[5] = 32'h9b05688c;
H[6] = 32'h1f83d9ab;
H[7] = 32'h5be0cd19;

K[0] = 32'h428a2f98; 
K[1] = 32'h71374491;
K[2] = 32'hb5c0fbcf;
K[3] = 32'he9b5dba5;
K[4] = 32'h3956c25b;
K[5] = 32'h59f111f1;
K[6] = 32'h923f82a4;
K[7] = 32'hab1c5ed5;
K[8] = 32'hd807aa98;
K[9] = 32'h12835b01;
K[10] = 32'h243185be;
K[11] = 32'h550c7dc3;
K[12] = 32'h72be5d74;
K[13] = 32'h80deb1fe;
K[14] = 32'h9bdc06a7;
K[15] = 32'hc19bf174;
K[16] = 32'he49b69c1;
K[17] = 32'hefbe4786;
K[18] = 32'h0fc19dc6;
K[19] = 32'h240ca1cc;
K[20] = 32'h2de92c6f;
K[21] = 32'h4a7484aa;
K[22] = 32'h5cb0a9dc;
K[23] = 32'h76f988da;
K[24] = 32'h983e5152;
K[25] = 32'ha831c66d;
K[26] = 32'hb00327c8;
K[27] = 32'hbf597fc7;
K[28] = 32'hc6e00bf3;
K[29] = 32'hd5a79147;
K[30] = 32'h06ca6351;
K[31] = 32'h14292967;
K[32] = 32'h27b70a85;
K[33] = 32'h2e1b2138;
K[34] = 32'h4d2c6dfc;
K[35] = 32'h53380d13;
K[36] = 32'h650a7354;
K[37] = 32'h766a0abb;
K[38] = 32'h81c2c92e;
K[39] = 32'h92722c85;
K[40] = 32'ha2bfe8a1;
K[41] = 32'ha81a664b;
K[42] = 32'hc24b8b70;
K[43] = 32'hc76c51a3;
K[44] = 32'hd192e819;
K[45] = 32'hd6990624;
K[46] = 32'hf40e3585;
K[47] = 32'h106aa070;
K[48] = 32'h19a4c116;
K[49] = 32'h1e376c08;
K[50] = 32'h2748774c;
K[51] = 32'h34b0bcb5;
K[52] = 32'h391c0cb3;
K[53] = 32'h4ed8aa4a;
K[54] = 32'h5b9cca4f;
K[55] = 32'h682e6ff3;
K[56] = 32'h748f82ee;
K[57] = 32'h78a5636f;
K[58] = 32'h84c87814;
K[59] = 32'h8cc70208;
K[60] = 32'h90befffa;
K[61] = 32'ha4506ceb;
K[62] = 32'hbef9a3f7;
K[63] = 32'hc67178f2;
end

always @(posedge clk)
begin
	if(index == 127)
	begin
		a <= H[0];
		b <= H[1];
		c <= H[2];
		d <= H[3];
		e <= H[4];
		f <= H[5];
		g <= H[6];
		h <= H[7];
	end
	if(index<16)
		W[index] <= word;
	else if(index<64)
	begin
		p = {W[index-2][16:0],W[index-2][31:17]}^{W[index-2][18:0],W[index-2][31:19]}^(W[index-2]>>10);
		q = W[index-7];
		r = {W[index-15][6:0],W[index-15][31:7]}^{W[index-15][17:0],W[index-15][31:18]}^(W[index-15]>>3);
		x = W[index-16];
		W[index] <= p + q + r +x;
	end
	index <= index + 1;
end

always @(posedge clk)
begin 
	if(index>0 && index <65)
	begin
		sum1 = {e[5:0],e[31:6]}^{e[10:0],e[31:11]}^{e[24:0],e[31:25]};
		sum0 = {a[1:0],a[31:2]}^{a[12:0],a[31:13]}^{a[21:0],a[31:22]};
		Ch = (e&f)^((~e)&g);
		Maj = (a&b)^(b&c)^(c&a);
		T1 = h + sum1 + Ch +K[index-1] + W[index-1];
		T2 = sum0 + Maj;
		h <= g;
		g <= f;
		f <= e;
		e <= d + h + sum1 + Ch + K[index-1]+ W[index-1];
		d <= c;
		c <= b;
		b <= a;
		a <= T1 + T2;
		
	end
	if(index == 65)
	begin
		H[0] <= a + H[0];
		H[1] <= b + H[1];
		H[2] <= c + H[2];
		H[3] <= d + H[3];
		H[4] <= e + H[4];
		H[5] <= f + H[5];
		H[6] <= g + H[6];
		H[7] <= h + H[7];
		index <= 127;
		if(last_word == 1 && (last_next[0] == 1'b1 || D == 1'b1))
		begin
			output_valid = 1'b1;
		end
		if(last_next[1] == 1'b1)
		begin
			D <= 1'b1;
		end
	end
end

assign hash_data = {H[0],H[1],H[2],H[3],H[4],H[5],H[6],H[7]};
endmodule

实验3(SHA2)/sha256.v
`include "sha_engine.v"
module sha256(input_data,input_valid,input_ready,last_word,clk,rst,output_valid,hash_data);

input [31:0]input_data;
input input_valid;
input last_word;
input clk,rst;

output reg input_ready;
output wire [255:0]hash_data;
output wire output_valid;

wire [6:0]block_counter;
reg [4:0] length_counter;
reg [63:0]size;
reg [1:0]special;
reg [31:0]output_data;
reg D;
reg last_word_delayed;
reg [1:0]last_next;


always @(negedge rst)
begin
last_next = 2'b00;
input_ready <= 1'b1;
length_counter <= 5'd31;
special <= 2'd0;
size <= 64'hffffffffffffffe0;
D <= 1'b1;
last_word_delayed <= 1'b0;
end


sha_engine Eng(output_data,clk,block_counter,rst,output_valid,hash_data,last_word,last_next);

always @(posedge clk)
begin

	if(input_valid == 1'b1 && input_ready == 1'b1)
	begin
		if(length_counter == 5'd14)
			input_ready <= 1'b0;

		length_counter = length_counter + 1;
	end
	
end

always @(posedge clk)
begin
	if(last_word == 1'b1)
		last_word_delayed <= 1'b1;
end

always @(posedge last_word_delayed)
begin
	if(length_counter<=13)
		special <= 2'b01;
	else
		special <= 2'b11;
end

always @(posedge clk)
begin
	case(special)
		2'b00 : begin
			output_data <= input_data;
			last_next <= 2'b00;
			end
		2'b01 : begin
			last_next <= 2'b01;

			if(length_counter<15)
			begin
				if(length_counter == 1 && size == 512)
					output_data <= {1'b1,{31{1'b0}}};
				else 
				begin
				D <= 1'b0;
				output_data <= {D,{31{1'b0}}};
				end
			end
			else if(length_counter == 15)
			begin
				output_data <= size[63:32];
				length_counter <= length_counter + 1;
			end
			else
				output_data <= size[31:0];
			end
		2'b11 : begin
				last_next <= 2'b10;
				D <= 1'b0;
				output_data <= {D,{31{1'b0}}};

			end
	endcase
end

always @(posedge clk)
begin
	if(block_counter == 64)
	begin
		length_counter <= 5'd31;
		input_ready <= 1'b1;
	end
	if(block_counter == 65)
	begin
		if(special == 3)
			special <= 2'b01;
		else
			special <= 2'd0;
	end
end

always @(posedge clk)
begin
	if(input_ready == 1 && special == 0)
		size <=  size + 32;
end

always @(posedge last_word)
begin
	if(length_counter == 15)
		size <= size + 32;
end
endmodule

实验3(SHA2)/tb_sha256.v
`include "sha256.v"
module tb_sha256();

reg [31:0]input_data;
reg input_valid;
reg last_word;
reg [6:0]blocks;
reg clk;
reg rst;
wire [255:0]hash_data;
wire output_valid;
integer fd,scan_file;

initial begin
clk = 1'b0;
last_word = 1'b0;
input_valid = 1'b1;
blocks = 0;
fd = $fopen("C:/Users/rhett/Desktop/SHA-256/my_file.txt","r");  
rst = 1'b1;
#2;
rst = 1'b0;
end

initial
begin            
    $dumpfile("wave.vcd");        //生成的vcd文件名称
    $dumpvars();    //tb模块名称
end 

sha256 UUT(input_data,input_valid,input_ready,last_word,clk,rst,output_valid,hash_data);

always #10 clk = (~output_valid)^clk;

always @(posedge clk)
begin
	if(input_ready==1'b1 && last_word == 1'b0)
	begin
		scan_file = $fscanf(fd, "%x\n", input_data); 
		blocks <= blocks + 1;
	end
end

always @(blocks)
begin

	if(blocks == 24)						 /*  Change the no. of 32 bit blocks here*/
		last_word = 1'b1;
end

endmodule

实验3(SHA2)/wave.vcd
$date
	Mon Dec 25 22:35:19 2023
$end
$version
	Icarus Verilog
$end
$timescale
	1s
$end
$scope module tb_sha256 $end
$var wire 1 ! output_valid $end
$var wire 1 " input_ready $end
$var wire 256 # hash_data [255:0] $end
$var reg 7 $ blocks [6:0] $end
$var reg 1 % clk $end
$var reg 32 & input_data [31:0] $end
$var reg 1 ' input_valid $end
$var reg 1 ( last_word $end
$var reg 1 ) rst $end
$var integer 32 * fd [31:0] $end
$var integer 32 + scan_file [31:0] $end
$scope module UUT $end
$var wire 1 % clk $end
$var wire 32 , input_data [31:0] $end
$var wire 1 ' input_valid $end
$var wire 1 ( last_word $end
$var wire 1 ) rst $end
$var wire 1 ! output_valid $end
$var wire 256 - hash_data [255:0] $end
$var wire 7 . block_counter [6:0] $end
$var reg 1 / D $end
$var reg 1 " input_ready $end
$var reg 2 0 last_next [1:0] $end
$var reg 1 1 last_word_delayed $end
$var reg 5 2 length_counter [4:0] $end
$var reg 32 3 output_data [31:0] $end
$var reg 64 4 size [63:0] $end
$var reg 2 5 special [1:0] $end
$scope module Eng $end
$var wire 1 % clk $end
$var wire 2 6 last_next [1:0] $end
$var wire 1 ( last_word $end
$var wire 1 ) rst $end
$var wire 32 7 word [31:0] $end
$var wire 256 8 hash_data [255:0] $end
$var reg 32 9 Ch [31:0] $end
$var reg 1 : D $end
$var reg 32 ; Maj [31:0] $end
$var reg 32 < T1 [31:0] $end
$var reg 32 = T2 [31:0] $end
$var reg 32 > a [31:0] $end
$var reg 32 ? b [31:0] $end
$var reg 32 @ c [31:0] $end
$var reg 32 A d [31:0] $end
$var reg 32 B e [31:0] $end
$var reg 32 C f [31:0] $end
$var reg 32 D g [31:0] $end
$var reg 32 E h [31:0] $end
$var reg 7 F index [6:0] $end
$var reg 1 ! output_valid $end
$var reg 32 G p [31:0] $end
$var reg 32 H q [31:0] $end
$var reg 32 I r [31:0] $end
$var reg 32 J sum0 [31:0] $end
$var reg 32 K sum1 [31:0] $end
$var reg 32 L x [31:0] $end
$upscope $end
$upscope $end
$upscope $end
$enddefinitions $end
$comment Show the parameter values. $end
$dumpall
$end
#0
$dumpvars
bx L
bx K
bx J
bx I
bx H
bx G
bx F
bx E
bx D
bx C
bx B
bx A
bx @
bx ?
bx >
bx =
bx <
bx ;
x:
bx 9
bx 8
bx 7
bx 6
bx 5
bx 4
bx 3
bx 2
x1
bx 0
x/
bx .
bx -
bx ,
bx +
b10000000000000000000000000000011 *
1)
0(
1'
bx &
0%
b0 $
bx #
x"
x!
$end
#2
01
1/
b1111111111111111111111111111111111111111111111111111111111100000 4
b0 5
b11111 2
1"
b110101000001001111001100110011110111011011001111010111010000101001111000110111011110011011100101010010101001111111101010011101001010001000011100101001001111111100110110000010101101000100011000001111110000011110110011010101101011011111000001100110100011001 #
b110101000001001111001100110011110111011011001111010111010000101001111000110111011110011011100101010010101001111111101010011101001010001000011100101001001111111100110110000010101101000100011000001111110000011110110011010101101011011111000001100110100011001 -
b110101000001001111001100110011110111011011001111010111010000101001111000110111011110011011100101010010101001111111101010011101001010001000011100101001001111111100110110000010101101000100011000001111110000011110110011010101101011011111000001100110100011001 8
0!
b1111110 .
b1111110 F
0:
b0 0
b0 6
0)
#10
b1111111 .
b1111111 F
b1101101000111100111001010101101 3
b1101101000111100111001010101101 7
b0 4
b1 $
b0 2
b1 +
b1101101000111100111001010101101 &
b1101101000111100111001010101101 ,
1%
#20
0%
#30
b10 $
b100000 4
b0 .
b0 F
b1011011111000001100110100011001 E
b11111100000111101100110101011 D
b10011011000001010110100010001100 C
b1010001000011100101001001111111 B
b10100101010011111111010100111010 A
b111100011011101111001101110010 @
b10111011011001111010111010000101 ?
b1101010000010011110011001100111 >
b11110111011110101101011101 &
b11110111011110101101011101 ,
b1 2
1%
#40
0%
#50
b1 .
b1 F
b11101000100100011110010101110010 3
b11101000100100011110010101110010 7
b1000000 4
b11 $
b10 2
b11101000100100011110010101110010 &
b11101000100100011110010101110010 ,
1%
#60
0%
#70
b100 $
b1100000 4
b1101001001001101111101011111010 >
b1101010000010011110011001100111 ?
b10111011011001111010111010000101 @
b111100011011101111001101110010 A
b101111001100101010101001111 B
b1010001000011100101001001111111 C
b10011011000001010110100010001100 D
b11111100000111101100110101011 E
b10 .
b10 F
b11100010001110010110111110001101 &
b11100010001110010110111110001101 ,
b11 2
b1000100100001001101011100101 =
b1100000100101100110000000010101 <
b111010011011111110011001100111 ;
b11111100001011100100110001100 9
b11001110001000001011010001111110 J
b110101100001110010011100101011 K
1%
#80
0%
#90
b11 .
b11 F
b10111100110010110000101110101110 >
b1101001001001101111101011111010 ?
b1101010000010011110011001100111 @
b10111011011001111010111010000101 A
b10110111101000001111001000001100 B
b101111001100101010101001111 C
b1010001000011100101001001111111 D
b10011011000001010110100010001100 E
b10100000000101011101100010011001 3
b10100000000101011101100010011001 7
b10000000 4
b101 $
b1000001100110010000110100010100 =
b1111011001100011111111010011010 <
b1101011001001111110111011100111 ;
b10011011000001110111100011001111 9
b11010110011100010001111000101101 J
b1100110110111011000001000011101 K
b100 2
b10100000000101011101100010011001 &
b10100000000101011101100010011001 ,
1%
#100
0%
#110
b110 $
b10100000 4
b1101000101011011001010100000111 >
b10111100110010110000101110101110 ?
b1101001001001101111101011111010 @
b1101010000010011110011001100111 A
b11011101100111111011101001011110 B
b10110111101000001111001000001100 C
b101111001100101010101001111 D
b1010001000011100101001001111111 E
b100 .
b100 F
b11101111000011100111100101010000 &
b11101111000011100111100101010000 ,
b101 2
b1000110011101011000100100101110 =
b100010001110000000101111011001 <
b1101000000010111110101011101110 ;
b1000101101011100101000001111111 9
b11011110011010011001111001000000 J
b10100011001100010111000110001101 K
1%
#120
0%
#130
b101 .
b101 F
b10011101000111111011100101110111 >
b1101000101011011001010100000111 ?
b10111100110010110000101110101110 @
b1101001001001101111101011111010 A
b11011010001101011100011010100001 B
b11011101100111111011101001011110 C
b10110111101000001111001000001100 D
b101111001100101010101001111 E
b110001010100101101011000000001 3
b110001010100101101011000000001 7
b11000000 4
b111 $
b101100111100111101100100111101 =
b1110000001010111110000000111010 <
b1101000101011111001101110101110 ;
b10010101111000001111011100001101 9
b11000100010001000011110110001111 J
b11111111011100001110001001110000 K
b110 2
b110001010100101101011000000001 &
b110001010100101101011000000001 ,
1%
#140
0%
#150
b1000 $
b11100000 4
b110101010001111101010110011001 >
b10011101000111111011100101110111 ?
b1101000101011011001010100000111 @
b10111100110010110000101110101110 A
b10001111110000000101111010011000 B
b11011010001101011100011010100001 C
b11011101100111111011101001011110 D
b10110111101000001111001000001100 E
b110 .
b110 F
b1010001111111110011010010001 &
b1010001111111110011010010001 ,
b111 2
b1110101011100111000111111011 =
b100110100110010110001110011110 <
b10111100100011111001100100100111 ;
b11111101100101011011001000001100 9
b1010010000111101101100011010100 J
b1001001101100001100000101001111 K
1%
#160
0%
#170
b111 .
b111 F
b10101001111001000100011010011110 >
b110101010001111101010110011001 ?
b10011101000111111011100101110111 @
b1101000101011011001010100000111 A
b101010110100011000000110101000 B
b10001111110000000101111010011000 C
b11011010001101011100011010100001 D
b11011101100111111011101001011110 E
b1101101000111100111001010101101 3
b1101101000111100111001010101101 7
b100000000 4
b1001 $
b111011110111011101000010100100 =
b1101110000001100111010111111010 <
b111101000011111001010100010111 ;
b11011010000111111110011011000110 9
b11111110110011100011101110001101 J
b1010001000000011011010100110110 K
b1000 2
b1101101000111100111001010101101 &
b1101101000111100111001010101101 ,
1%
#180
0%
#190
b1010 $
b100100000 4
b1000110011000110001101101110000 >
b10101001111001000100011010011110 ?
b110101010001111101010110011001 @
b10011101000111111011100101110111 A
b11100010001100101011011010110110 B
b101010110100011000000110101000 C
b10001111110000000101111010011000 D
b11011010001101011100011010100001 E
b1000 .
b1000 F
b11110111011110101101011101 &
b11110111011110101101011101 ,
b1001 2
b11001100110111011111100111000001 =
b1111001100001010010000110101111 <
b10111101010001111101010110011111 ;
b11011010111001000100011010001001 9
b1111100101100010010000100010 J
b11111101011011101100100000100011 K
1%
#200
0%
#210
b1001 .
b1001 F
b10100010001011111100010100111101 >
b1000110011000110001101101110000 ?
b10101001111001000100011010011110 @
b110101010001111101010110011001 A
b11010011011100001111001000111111 B
b11100010001100101011011010110110 C
b101010110100011000000110101000 D
b10001111110000000101111010011000 E
b11101000100100011110010101110010 3
b11101000100100011110010101110010 7
b101000000 4
b1011 $
b1101011110111101000110001110101 =
b110110010100010011100011001000 <
b100101011001110101011110011000 ;
b101111110100001100100010101000 9
b1000110011101110011010011011101 J
b10100000011111101011111111101 K
b1010 2
b11101000100100011110010101110010 &
b11101000100100011110010101110010 ,
1%
#220
0%
#230
b1100 $
b101100000 4
b1100001010000000011111111000111 >
b10100010001011111100010100111101 ?
b1000110011000110001101101110000 @
b10101001111001000100011010011110 A
b11110101101011101011011101101011 B
b11010011011100001111001000111111 C
b11100010001100101011011010110110 D
b101010110100011000000110101000 E
b1010 .
b1010 F
b11100010001110010110111110001101 &
b11100010001110010110111110001101 ,
b1011 2
b10100000110110010101110111110101 =
b11000000011001101110000111010010 <
b10100010011001110100011100111100 ;
b11101010101100011011001110110110 9
b11111110011100100001011010111001 J
b110011101011001000111111 K
1%
#240
0%
#250
b1011 .
b1011 F
b11000000000100110011110110101 >
b1100001010000000011111111000111 ?
b10100010001011111100010100111101 @
b1000110011000110001101101110000 A
b111000111011110111011001101001 B
b11110101101011101011011101101011 C
b11010011011100001111001000111111 D
b11100010001100101011011010110110 E
b10100000000101011101100010011001 3
b10100000000101011101100010011001 7
b110000000 4
b1101 $
b10001000111101110011011111101010 =
b10001111000010110010111111001011 <
b1100010011000110001111101110101 ;
b11010011001100001011001010111111 9
b100110100101000001100001110101 J
b10010101111100111011101011110001 K
b1100 2
b10100000000101011101100010011001 &
b10100000000101011101100010011001 ,
1%
#260
0%
#270
b1110 $
b110100000 4
b10010011011011010110001001100011 >
b11000000000100110011110110101 ?
b1100001010000000011111111000111 @
b10100010001011111100010100111101 A
b1000111100101111000100010000000 B
b111000111011110111011001101001 C
b11110101101011101011011101101011 D
b11010011011100001111001000111111 E
b1100 .
b1100 F
b11101111000011100111100101010000 &
b11101111000011100111100101010000 ,
b1101 2
b10010010001110001111010101010011 =
b1001101000110110100010000 <
b100000000000100110011110110101 ;
b11110011101111101011011001111111 9
b1110010001101101000110110011110 J
b11110011111111001010010101011 K
1%
#280
0%
#290
b1101 .
b1101 F
b10100111101001000010001010011011 >
b10010011011011010110001001100011 ?
b11000000000100110011110110101 @
b1100001010000000011111111000111 A
b11110110010001010011001000110011 B
b1000111100101111000100010000000 C
b111000111011110111011001101001 D
b11110101101011101011011101101011 E
b110001010100101101011000000001 3
b110001010100101101011000000001 7
b111000000 4
b1111 $
b1010011100011101011010110100101 =
b1010100000101010110110011110110 <
b10001010000000110011111100111 ;
b10110000101011110011011101101011 9
b1000010010011100100110110111110 J
b11011010110100101110110011110000 K
b1110 2
b110001010100101101011000000001 &
b110001010100101101011000000001 ,
1%
#300
0%
#310
b10000 $
b111100000 4
0"
b11010100111011010100100001 >
b10100111101001000010001010011011 ?
b10010011011011010110001001100011 @
b11000000000100110011110110101 A
b1100011101100010011011100011100 B
b11110110010001010011001000110011 C
b1000111100101111000100010000000 D
b111000111011110111011001101001 E
b1110 .
b1110 F
b1010001111111110011010010001 &
b1010001111111110011010010001 ,
b1111 2
b111000101011110111001100 =
b10011100001111011101010101 <
b10010011001001000110001010110011 ;
b1001110101011110100010001001000 9
b1101101101111100101101100011001 J
b10101011001111101100010110010101 K
1%
#320
0%
#330
b1111 .
b1111 F
b11000110001011111000101110111110 >
b11010100111011010100100001 ?
b10100111101001000010001010011011 @
b10010011011011010110001001100011 A
b10110011110001000101110101111000 B
b1100011101100010011011100011100 C
b11110110010001010011001000110011 D
b1000111100101111000100010000000 E
b1010001111111110011010010001 3
b1010001111111110011010010001 7
b101010011011011001010111111011 =
b10011011110000011111010111000011 <
b10000011011001010010001000100011 ;
b1100110000001111011101010010000 9
b10100111000010000111001111011000 J
b1001010100110010011110011001011 K
1%
#340
0%
#350
b101101110100011111000110000 >
b11000110001011111000101110111110 ?
b11010100111011010100100001 @
b10100111101001000010001010011011 A
b10111111101011001101010001001101 B
b10110011110001000101110101111000 C
b1100011101100010011011100011100 D
b11110110010001010011001000110011 E
b10000 .
b10000 F
b11011001011110101100110001000110 =
b101100001111110111000111101010 <
b10000111001001111010001110111011 ;
b1100111100000010011011100011011 9
b1010010010100110010100010001011 J
b10101111111101111101010110100111 K
1%
#360
0%
#370
b10001 .
b10001 F
b111110001011000000001100011111 >
b101101110100011111000110000 ?
b11000110001011111000101110111110 @
b11010100111011010100100001 A
b11000110011111100000010000111111 B
b10111111101011001101010001001101 C
b10110011110001000101110101111000 D
b1100011101100010011011100011100 E
b1101101000111100111001010101101 L
b10000001100111111010010101000000 I
b11101000100100011110010101110010 H
b110001110011001110101000110110 G
b11111010100100010000101111011 =
b11110110110011110000110100100 <
b111001110111011111100110000 ;
b11110011100101010111011101011000 9
b11000000101100110001001001011 J
b1101001001000110110000000010100 K
1%
#380
0%
#390
b10111110101001011010011010001111 >
b111110001011000000001100011111 ?
b101101110100011111000110000 @
b11000110001011111000101110111110 A
b1010100010011001100001100010011 B
b11000110011111100000010000111111 C
b10111111101011001101010001001101 D
b10110011110001000101110101111000 E
b10010 .
b10010 F
b1101101101011001001100010011101 =
b1010000111110010000110111110010 <
b110001011100000101100111110 ;
b10110111101011000101110101001101 9
b1100111011111101000110101011111 J
b1000111111000110010100000110011 K
b11101000100100011110010101110010 L
b1111100110000010101110100001 G
1%
#400
0%
#410
b10011 .
b10011 F
b10001011000111110101000011110011 >
b10111110101001011010011010001111 ?
b111110001011000000001100011111 @
b101101110100011111000110000 A
b11000101010101000001010000011110 B
b1010100010011001100001100010011 C
b11000110011111100000010000111111 D
b10111111101011001101010001001101 E
b1010001011001001111100010100111 I
b10100000000101011101100010011001 H
b11101111001110100110001010010100 G
b10001011111110101100100010010011 =
b11111111001001001000100001100000 <
b111110101011000010011000011111 ;
b11101111111011000001010001011111 9
b1001101010011101010001001110100 J
b1001010110100011001100111110 K
1%
#420
0%
#430
b1000001100001100011011000101 >
b10001011000111110101000011110011 ?
b10111110101001011010011010001111 @
b111110001011000000001100011111 A
b110111101001011011111101101100 B
b11000101010101000001010000011110 C
b1010100010011001100001100010011 D
b11000110011111100000010000111111 E
b10100 .
b10100 F
b11010110010001010100010110001001 =
b110001111010111000000100111100 <
b10111110001011010000001010011111 ;
b1000110011011100000000000110011 9
b11000000110000100001011101010 J
b1010010110001111111010110110000 K
b10100000000101011101100010011001 L
b10111110100000101000101110000000 G
1%
#440
0%
#450
b10101 .
b10101 F
b1010000111001110010111010110010 >
b1000001100001100011011000101 ?
b10001011000111110101000011110011 @
b10111110101001011010011010001111 A
b1001101100111100000011011110011 B
b110111101001011011111101101100 C
b11000101010101000001010000011110 D
b1010100010011001100001100010011 E
b10110001110010001011001100111000 I
b110001010100101101011000000001 H
b1101111101110011110110001001101 G
b1000001011101010010101011011110 =
b1111011100100000001111010100 <
b10001010001101011100011011000111 ;
b1000101010011000101010000011111 9
b10110111001111110110010000010111 J
b10001111100001111101010001010001 K
1%
#460
0%
#470
b1011100100010101101001101010011 >
b1010000111001110010111010110010 ?
b1000001100001100011011000101 @
b10001011000111110101000011110011 A
b10010101111001111010110100011001 B
b1001101100111100000011011110011 C
b110111101001011011111101101100 D
b11000101010101000001010000011110 E
b10110 .
b10110 F
b10000101010010001100110011001001 =
b11010111010000100000011010001010 <
b1000001101110100011011110011 ;
b10000101110001000001011001101100 9
b1111101000100011000010111010110 J
b11011100010111001011001001111101 K
b110001010100101101011000000001 L
b11111100000100111000011011000110 G
1%
#480
0%
#490
b10111 .
b10111 F
b111110000111000010100010001011 >
b1011100100010101101001101010011 ?
b1010000111001110010111010110010 @
b1000001100001100011011000101 A
b1001101000111001010010111011 B
b10010101111001111010110100011001 C
b1001101100111100000011011110011 D
b110111101001011011111101101100 E
b11001011110100101010100111110111 I
b1010001111111110011010010001 H
b11001110111100001011110111111011 G
b10111111100101111110010011000011 =
b1111110100001000100001111001000 <
b1011000101000101100011011010011 ;
b100111100001100001011001110101 9
b1100110111101010001110111110000 J
b110110101100111010111010001011 K
1%
#500
0%
#510
b10110011000001001111110010010111 >
b111110000111000010100010001011 ?
b1011100100010101101001101010011 @
b1010000111001110010111010110010 A
b1100011001010101100001010001110 B
b1001101000111001010010111011 C
b10010101111001111010110100011001 D
b1001101100111100000011011110011 E
b11000 .
b11000 F
b1011000000010110000000011001110 =
b1011010111110011111101111001001 <
b1011100100011100010101010010011 ;
b1000101101111111000011001011001 9
b11111011011111001101011000111011 J
b10101010100011011110011110100100 K
b1101101000111100111001010101101 L
b1001000111001110011110010101 H
b11001111110001000010101000101001 G
1%
#520
0%
#530
b11001 .
b11001 F
b11000011000011101110011110001110 >
b10110011000001001111110010010111 ?
b111110000111000010100010001011 @
b1011100100010101101001101010011 A
b10111010010110100010001111011111 B
b1100011001010101100001010001110 C
b1001101000111001010010111011 D
b10010101111001111010110100011001 E
b10000001100111111010010101000000 I
b1100010010110111001101111000101 H
b11010110111001110110010001101000 G
b1011001100110111111001001100001 =
b1101001011100101111010100101101 <
b111110000011001111100010010011 ;
b10010101111001111010110110011011 9
b11011100011101111100111001110 J
b11111101001000011000100101100011 K
1%
#540
0%
#550
b1100000110110000000001110000 >
b11000011000011101110011110001110 ?
b10110011000001001111110010010111 @
b111110000111000010100010001011 A
b11111110011011010100110010011100 B
b10111010010110100010001111011111 C
b1100011001010101100001010001110 D
b1001101000111001010010111011 E
b11010 .
b11010 F
b1101010001110001000011100100111 =
b10100001111000100111100101001001 <
b10110011000011001110110010001111 ;
b100011101010111001011010101110 9
b10110111001010111001101010011000 J
b101000000011111100110000010110 K
b11101000100100011110010101110010 L
b11001001010001110001100101000110 H
b1010010111110010011111001011000 G
1%
#560
0%
#570
b11011 .
b11011 F
b10111001111010000011110010000100 >
b1100000110110000000001110000 ?
b11000011000011101110011110001110 @
b10110011000001001111110010010111 A
b1000011011100001111110000101 B
b11111110011011010100110010011100 C
b10111010010110100010001111011111 D
b1100011001010101100001010001110 E
b1010001011001001111100010100111 I
b1010000000100110011010101011001 H
b10101111000001000101000101000110 G
b11101111100101100100010110001010 =
b11001010010100011111011011111010 <
b10000011000011101110010010010110 ;
b10111011010010101000001010011110 9
b1101100100001110110000011110100 J
b11010110110000000011011011100100 K
1%
#580
0%
#590
b11001101111111111110101000110000 >
b10111001111010000011110010000100 ?
b1100000110110000000001110000 @
b11000011000011101110011110001110 A
b10001101010011001110111110111100 B
b1000011011100001111110000101 C
b11111110011011010100110010011100 D
b10111010010110100010001111011111 E
b11100 .
b11100 F
b11110011101101111111011100001011 =
b11011010010001111111001100100101 <
b10001001000010100010010010000100 ;
b10111010011111000010110011011110 9
b1101010101011011101001010000111 J
b11010011100011110111011100111001 K
b10100000000101011101100010011001 L
b11110010111010110100111000011111 H
b11001101010000111100111110001110 G
1%
#600
0%
#610
b11101 .
b11101 F
b1110100111010100110010011110000 >
b11001101111111111110101000110000 ?
b10111001111010000011110010000100 @
b1100000110110000000001110000 A
b1100101011001100111000001010 B
b10001101010011001110111110111100 C
b1000011011100001111110000101 D
b11111110011011010100110010011100 E
b10110001110010001011001100111000 I
b10000100000011110011000000000 H
b11111110110001010101100000111111 G
b101011010011000111111001110100 =
b1001001100111011110011001111100 <
b10001101111110110010100000110000 ;
b1111010011011010000111110000100 9
b10011101010100010101011001000100 J
b10100011110100110100010001100101 K
1%
#620
0%
#630
b10000010111010111001001000111111 >
b1110100111010100110010011110000 ?
b11001101111111111110101000110000 @
b10111001111010000011110010000100 A
b11111101111100010010011001000011 B
b1100101011001100111000001010 C
b10001101010011001110111110111100 D
b1000011011100001111110000101 E
b11110 .
b11110 F
b10010001000101010110110001101100 =
b11110001110101100010010111010011 <
b11111101111010100110110010110000 ;
b1100010011101101111110001101 9
b10010011001010101111111110111100 J
b10111111000101000010001110100111 K
b110001010100101101011000000001 L
b11010110010101100010010010000100 H
b11001010100001110000010010011010 G
1%
#640
0%
#650
b11111 .
b11111 F
b1010001110100000111111000101100 >
b10000010111010111001001000111111 ?
b1110100111010100110010011110000 @
b11001101111111111110101000110000 A
b1100111101111101100101010101000 B
b11111101111100010010011001000011 C
b1100101011001100111000001010 D
b10001101010011001110111110111100 E
b11011010111101111100000110010000 I
b10001110100100010111001100010 H
b1011100010100100111010111000100 G
b10100011111110011111000000001000 =
b10101101110101101000111000100100 <
b11000100111010111110001000110000 ;
b1100101011001100111110111110 9
b11011111000011100000110111011000 J
b111111000110110101101101000011 K
1%
#660
0%
#670
b10011110000001101000010000010001 >
b1010001110100000111111000101100 ?
b10000010111010111001001000111111 @
b1110100111010100110010011110000 A
b1110110001011011101011110110110 B
b1100111101111101100101010101000 C
b11111101111100010010011001000011 D
b1100101011001100111000001010 E
b100000 .
b100000 F
b11110101110110001001011010001011 =
b10101000001011011110110110000110 <
b1010000111010100111011000111100 ;
b1101101101100000000011000000010 9
b10100100111011100010000001001111 J
b101011111101110101100011000000 K
b1010001111111110011010010001 L
b10010110101001110011101111010 I
b101000000000010001100000011010 H
b1001111010000011100111110101111 G
1%
#680
0%
#690
b100001 .
b100001 F
b11001111000001111110011110001010 >
b10011110000001101000010000010001 ?
b1010001110100000111111000101100 @
b10000010111010111001001000111111 A
b1010100000100101001111011110101 B
b1110110001011011101011110110110 C
b1100111101111101100101010101000 D
b11111101111100010010011001000011 E
b1001000111001110011110010101 L
b1100000011111101001110011011001 I
b10000110011100011110001001010000 H
b1111010101100111100100110110100 G
b11101111110111111010110110000101 =
b11011111001010000011101000000101 <
b10010010110000101001011000111101 ;
b11101111111111001110001011100001 9
b1011101000111010001011101001000 J
b111001111111011010100111011111 K
1%
#700
0%
